setup.cfg
setup.py
pyf/__init__.py
pyf.components.postprocess.files_post_handler.egg-info/PKG-INFO
pyf.components.postprocess.files_post_handler.egg-info/SOURCES.txt
pyf.components.postprocess.files_post_handler.egg-info/dependency_links.txt
pyf.components.postprocess.files_post_handler.egg-info/entry_points.txt
pyf.components.postprocess.files_post_handler.egg-info/namespace_packages.txt
pyf.components.postprocess.files_post_handler.egg-info/requires.txt
pyf.components.postprocess.files_post_handler.egg-info/top_level.txt
pyf.components.postprocess.files_post_handler.egg-info/zip-safe
pyf/components/__init__.py
pyf/components/postprocess/__init__.py
pyf/components/postprocess/files_post_handler/__init__.py
pyf/components/postprocess/files_post_handler/postprocess.py