Metadata-Version: 1.0
Name: pyf.components.postprocess.files-post-handler
Version: 0.2
Summary: Handle files during post process
Home-page: http://pyfproject.org
Author: Mathieu Bridon
Author-email: mathieu.bridon@gmail.com
License: MIT
Platform: UNKNOWN
Classifier: Development Status :: 3 - Alpha
Classifier: Operating System :: OS Independent
Classifier: Programming Language :: Python
Classifier: License :: OSI Approved :: MIT License
Classifier: Topic :: Software Development :: Libraries :: Python Modules
